porerefiner/__init__.py
porerefiner/cli.py
porerefiner/cli_utils.py
porerefiner/config.py
porerefiner/daemon.py
porerefiner/fsevents.py
porerefiner/models.py
porerefiner/porerefiner.app.service
porerefiner/porerefiner.py
porerefiner/porerefiner.service
porerefiner/rpc.py
porerefiner/app/__init__.py
porerefiner/app/main.py
porerefiner/app/page.py
porerefiner/app/templates/run_view.html
porerefiner/app/templates/submit.html
porerefiner/app/templates/view.html
porerefiner/jobs/__init__.py
porerefiner/jobs/generic.py
porerefiner/jobs/submitters/__init__.py
porerefiner/jobs/submitters/hpc.py
porerefiner/jobs/submitters/local.py
porerefiner/notifiers/__init__.py
porerefiner/notifiers/http.py
porerefiner/notifiers/sqs.py
porerefiner/notifiers/toast.py
porerefiner/protocols/__init__.py
porerefiner/protocols/minknow/__init__.py
porerefiner/protocols/minknow/rpc/__init__.py
porerefiner/protocols/minknow/rpc/acquisition.proto
porerefiner/protocols/minknow/rpc/acquisition_grpc.py
porerefiner/protocols/minknow/rpc/acquisition_pb2.py
porerefiner/protocols/minknow/rpc/device.proto
porerefiner/protocols/minknow/rpc/device_grpc.py
porerefiner/protocols/minknow/rpc/device_pb2.py
porerefiner/protocols/minknow/rpc/instance.proto
porerefiner/protocols/minknow/rpc/instance_grpc.py
porerefiner/protocols/minknow/rpc/instance_pb2.py
porerefiner/protocols/minknow/rpc/keystore.proto
porerefiner/protocols/minknow/rpc/keystore_grpc.py
porerefiner/protocols/minknow/rpc/keystore_pb2.py
porerefiner/protocols/minknow/rpc/manager.proto
porerefiner/protocols/minknow/rpc/manager_grpc.py
porerefiner/protocols/minknow/rpc/manager_pb2.py
porerefiner/protocols/minknow/rpc/protocol.proto
porerefiner/protocols/minknow/rpc/protocol_grpc.py
porerefiner/protocols/minknow/rpc/protocol_pb2.py
porerefiner/protocols/minknow/rpc/rpc_options.proto
porerefiner/protocols/minknow/rpc/rpc_options_grpc.py
porerefiner/protocols/minknow/rpc/rpc_options_pb2.py
porerefiner/protocols/porerefiner/__init__.py
porerefiner-0.9.5.dist-info/AUTHORS.rst
porerefiner-0.9.5.dist-info/LICENSE
porerefiner-0.9.5.dist-info/METADATA
porerefiner-0.9.5.dist-info/WHEEL
porerefiner-0.9.5.dist-info/entry_points.txt
porerefiner-0.9.5.dist-info/top_level.txt
porerefiner-0.9.5.dist-info/RECORD
