Metadata-Version: 2.1
Name: porerefiner
Version: 0.9.5
Summary: To help you manage your pores
Home-page: https://github.com/CFSAN-Biostatistics/porerefiner
Author: Justin Payne
Author-email: justin.payne@fda.hhs.gov
License: MIT license
Keywords: porerefiner
Platform: UNKNOWN
Classifier: Development Status :: 2 - Pre-Alpha
Classifier: Intended Audience :: Developers
Classifier: License :: OSI Approved :: MIT License
Classifier: Natural Language :: English
Classifier: Programming Language :: Python :: 3.8
Requires-Python: >=3.8
Requires-Dist: Click (~=7.0)
Requires-Dist: flask (~=1.1.1)
Requires-Dist: peewee (~=3.13.3)
Requires-Dist: gunicorn (~=19.9.0)
Requires-Dist: watchdog (~=0.9.0)
Requires-Dist: hachiko (~=0.2.0)
Requires-Dist: aiohttp (~=3.6.1)
Requires-Dist: aiofile (~=3.0.0)
Requires-Dist: namesgenerator (~=0.3)
Requires-Dist: python-daemon (~=2.2.3)
Requires-Dist: protobuf (~=3.17)
Requires-Dist: grpclib (~=0.4.1)
Requires-Dist: tabulate (~=0.8.5)
Requires-Dist: asyncssh (~=2.0.1)
Requires-Dist: setproctitle (~=1.1.10)
Requires-Dist: pyyaml (~=5.3)
